Workbook

Sheet 说明
B2: 瓦轴集团ABC成本核算模型
B3: Activity-Based Costing Model
B5: 模型版本： | C5: V1.0
B6: 创建日期： | C6: 2025年12月10日
B7: 适用范围： | C7: 精加工车间三分厂
B8: 核算期间： | C8: 2024年第四季度(10-12月)
B10: 使用说明：
B11: 1. 首先查看【基础数据】工作表，了解产品和生产信息
B12: 2. 查看【成本归集】工作表，了解制造费用构成
B13: 3. 查看【作业识别】和【成本动因】，了解ABC方法的核心
B14: 4. 系统自动计算【产品成本】，无需手动操作
B15: 5. 查看【成本对比】和【可视化图表】，了解ABC方法的价值
B17: 注意事项：
B18: • 浅黄色单元格为输入区（本模型为演示，数据已填充）
B19: • 浅蓝色单元格为自动计算区，请勿修改
B20: • 修改输入数据后，按F9刷新计算
B21: • 定期备份模型文件
B23: 项目组成员：
... B28: 顾问: __________ 联系方式: __________

Sheet 基础数据
A1: 产品信息表
A2: 产品编号 | B2: 产品型号 | C2: 产品名称 | D2: 产品类别 | E2: 季度产量(件) | F2: 批次数 | G2: 平均批量 | H2: 单位售价(元) | I2: 备注
A3: P001 | B3: 32315 | C3: 圆锥滚子轴承 | D3: 标准品 | E3: 60000 | F3: 30 | G3: 2000 | H3: 145 | I3: 主力产品,走量
A4: P002 | B4: 6320 | C4: 深沟球轴承 | D4: 标准品 | E4: 45000 | F4: 45 | G4: 1000 | H4: 92 | I4: 薄利多销
A5: P003 | B5: NU2316 | C5: 圆柱滚子轴承 | D5: 标准品 | E5: 18000 | F5: 36 | G5: 500 | H5: 280 | I5: 毛利较好
A6: P004 | B6: 定制-HD | C6: 高端定制轴承 | D6: 定制品 | E6: 1500 | F6: 30 | G6: 50 | H6: 1800 | I6: 技术门槛高
A7: P005 | B7: 定制-TP | C7: 特种工况轴承 | D7: 定制品 | E7: 300 | F7: 20 | G7: 15 | H7: 5500 | I7: 超高端定制
A8: 合计 | E8: =SUM(E3:E7) | F8: =SUM(F3:F7)
A10: 产品工时统计表
A11: 产品编号 | B11: 单件标准工时(h) | C11: 单件机器小时(h) | D11: 季度总人工(h) | E11: 季度总机时(h)
A12: P001 | B12: 0.4 | C12: 1.2 | D12: 24000 | E12: 72000
A13: P002 | B13: 0.3 | C13: 0.8 | D13: 13500 | E13: 36000
A14: P003 | B14: 0.6 | C14: 1.5 | D14: 10800 | E14: 27000
A15: P004 | B15: 2.5 | C15: 4 | D15: 3750 | E15: 6000
A16: P005 | B16: 5 | C16: 8 | D16: 1500 | E16: 2400
A17: 合计 | D17: =SUM(D12:D16) | E17: =SUM(E12:E16)
A19: 直接成本汇总表
A20: 产品编号 | B20: 直接材料(元) | C20: 直接人工(元) | D20: 直接成本合计(元) | E20: 单位直接成本(元)
A21: P001 | B21: 2880000 | C21: 1200000 | D21: =B21+C21 | E21: =D21/E3
A22: P002 | B22: 1170000 | C22: 675000 | D22: =B22+C22 | E22: =D22/E4
A23: P003 | B23: 1170000 | C23: 540000 | D23: =B23+C23 | E23: =D23/E5
A24: P004 | B24: 210000 | C24: 300000 | D24: =B24+C24 | E24: =D24/E6
A25: P005 | B25: 90000 | C25: 120000 | D25: =B25+C25 | E25: =D25/E7

Sheet 成本归集
A1: 制造费用汇总表（季度，元）
A2: 费用编号 | B2: 费用科目 | C2: 季度发生额(元) | D2: 占比 | E2: 归属性质 | F2: 备注
A3: C01 | B3: 设备折旧费 | C3: 2400000 | D3: =C3/C14 | E3: 与设备使用相关
A4: C02 | B4: 电费 | C4: 900000 | D4: =C4/C14 | E4: 与机器运行相关
A5: C03 | B5: 设备维修保养费 | C5: 480000 | D5: =C5/C14 | E5: 与设备使用相关
A6: C04 | B6: 工装模具折旧 | C6: 360000 | D6: =C6/C14 | E6: 与批次相关
A7: C05 | B7: 车间管理人员工资 | C7: 1260000 | D7: =C7/C14 | E7: 设施级
A8: C06 | B8: 间接生产人员工资 | C8: 840000 | D8: =C8/C14 | E8: 多种作业
A9: C07 | B9: 质检部门费用 | C9: 720000 | D9: =C9/C14 | E9: 与检验相关
A10: C08 | B10: 物料搬运费用 | C10: 360000 | D10: =C10/C14 | E10: 与搬运相关
A11: C09 | B11: 车间办公及低耗 | C11: 180000 | D11: =C11/C14 | E11: 设施级
A12: C10 | B12: 水费、蒸汽费 | C12: 240000 | D12: =C12/C14 | E12: 与生产相关
A13: C11 | B13: 其他制造费用 | C13: 160000 | D13: =C13/C14 | E13: 设施级
A14: 合计 | C14: =SUM(C3:C13) | D14: 100.0%

Sheet 作业识别
A1: 作业清单
A2: 作业编号 | B2: 作业名称 | C2: 作业层级 | D2: 作业描述 | E2: 作业成本(元) | F2: 占比 | G2: 备注
A3: A01 | B3: 车削加工 | C3: 单位级 | D3: 内外圈粗精车 | E3: 1680000 | F3: =E3/E23
A4: A02 | B4: 磨削加工 | C4: 单位级 | D4: 内外圈精密磨 | E4: 1440000 | F4: =E4/E23
A5: A03 | B5: 热处理 | C5: 单位级 | D5: 淬火回火 | E5: 720000 | F5: =E5/E23
A6: A04 | B6: 超精研 | C6: 单位级 | D6: 表面超精加工 | E6: 480000 | F6: =E6/E23
A7: A05 | B7: 清洗去毛刺 | C7: 单位级 | D7: 清洗处理 | E7: 240000 | F7: =E7/E23
A8: B01 | B8: 设备换型调整 | C8: 批次级 | D8: 工装更换调整 | E8: 800000 | F8: =E8/E23
A9: B02 | B9: 首件检验 | C9: 批次级 | D9: 批次首检 | E9: 240000 | F9: =E9/E23
A10: B03 | B10: 生产准备 | C10: 批次级 | D10: 领料排产 | E10: 160000 | F10: =E10/E23
A11: B04 | B11: 物料搬运 | C11: 批次级 | D11: 工序间搬运 | E11: 360000 | F11: =E11/E23
A12: B05 | B12: 批次质检 | C12: 批次级 | D12: 巡检抽检 | E12: 320000 | F12: =E12/E23
A13: B06 | B13: 包装入库 | C13: 批次级 | D13: 批次包装 | E13: 160000 | F13: =E13/E23
A14: C01 | B14: 工艺设计优化 | C14: 产品级 | D14: 新品工艺 | E14: 240000 | F14: =E14/E23
A15: C02 | B15: 专用工装制作 | C15: 产品级 | D15: 专用工装 | E15: 180000 | F15: =E15/E23
A16: C03 | B16: 程序编制调试 | C16: 产品级 | D16: 数控程序 | E16: 120000 | F16: =E16/E23
A17: C04 | B17: 试产验证 | C17: 产品级 | D17: 新品试产 | E17: 80000 | F17: =E17/E23
A18: D01 | B18: 车间管理 | C18: 设施级 | D18: 车间运营管理 | E18: 480000 | F18: =E18/E23
A19: D02 | B19: 设备日常维护 | C19: 设施级 | D19: 预防性维护 | E19: 200000 | F19: =E19/E23
A20: D03 | B20: 质量体系维护 | C20: 设施级 | D20: 质量管理 | E20: 160000 | F20: =E20/E23
A21: D04 | B21: 环境安全管理 | C21: 设施级 | D21: 5S安全 | E21: 120000 | F21: =E21/E23
A22: D05 | B22: 能源动力供应 | C22: 设施级 | D22: 水电气供应 | E22: 120000 | F22: =E22/E23
A23: 合计 | E23: =SUM(E3:E22) | F23: 100.0%

Sheet 成本动因
A1: 成本动因选择与分配率
A2: 作业编号 | B2: 作业名称 | C2: 成本动因 | D2: 动因总量 | E2: 作业成本(元) | F2: 分配率 | G2: 单位
A3: A01 | B3: 车削加工 | C3: 车削机时(h) | D3: 69000 | E3: 1680000 | F3: =E3/D3 | G3: 元/h
A4: A02 | B4: 磨削加工 | C4: 磨削机时(h) | D4: 61200 | E4: 1440000 | F4: =E4/D4 | G4: 元/h
A5: A03 | B5: 热处理 | C5: 热处理件数 | D5: 124800 | E5: 720000 | F5: =E5/D5 | G5: 元/件
A6: A04 | B6: 超精研 | C6: 超精研机时(h) | D6: 13200 | E6: 480000 | F6: =E6/D6 | G6: 元/h
A7: A05 | B7: 清洗去毛刺 | C7: 清洗件数 | D7: 124800 | E7: 240000 | F7: =E7/D7 | G7: 元/件
A8: B01 | B8: 设备换型调整 | C8: 换型次数 | D8: 161 | E8: 800000 | F8: =E8/D8 | G8: 元/次
A9: B02 | B9: 首件检验 | C9: 首检次数 | D9: 161 | E9: 240000 | F9: =E9/D9 | G9: 元/次
A10: B03 | B10: 生产准备 | C10: 生产批次 | D10: 161 | E10: 160000 | F10: =E10/D10 | G10: 元/批
A11: B04 | B11: 物料搬运 | C11: 搬运批次 | D11: 322 | E11: 360000 | F11: =E11/D11 | G11: 元/批
A12: B05 | B12: 批次质检 | C12: 巡检批次 | D12: 161 | E12: 320000 | F12: =E12/D12 | G12: 元/批
A13: B06 | B13: 包装入库 | C13: 包装批次 | D13: 161 | E13: 160000 | F13: =E13/D13 | G13: 元/批
A14: C01 | B14: 工艺设计优化 | C14: 产品种类 | D14: 2 | E14: 240000 | F14: =E14/D14 | G14: 元/种
... A22: D05 | B22: 能源动力供应 | C22: 机器小时 | D22: 143400 | E22: 120000 | F22: =E22/D22 | G22: 元/h

Sheet 产品成本(ABC)
A1: 产品完全成本汇总表（ABC方法）
A2: 产品编号 | B2: 产品型号 | C2: 产量(件) | D2: 直接材料 | E2: 直接人工 | F2: ABC制造费用 | G2: 完全成本 | H2: 单位成本 | I2: 单位售价 | J2: 单位毛利 | K2: 毛利率
A3: P001 | B3: 32315 | C3: 60000 | D3: 2880000 | E3: 1200000 | F3: 3168180 | G3: =D3+E3+F3 | H3: =G3/C3 | I3: =基础数据!H3 | J3: =I3-H3 | K3: =J3/I3
A4: P002 | B4: 6320 | C4: 45000 | D4: 1170000 | E4: 675000 | F4: 2468205 | G4: =D4+E4+F4 | H4: =G4/C4 | I4: =基础数据!H4 | J4: =I4-H4 | K4: =J4/I4
A5: P003 | B5: NU2316 | C5: 18000 | D5: 1170000 | E5: 540000 | F5: 1382163 | G5: =D5+E5+F5 | H5: =G5/C5 | I5: =基础数据!H5 | J5: =I5-H5 | K5: =J5/I5
A6: P004 | B6: 定制-HD | C6: 1500 | D6: 210000 | E6: 300000 | F6: 596652 | G6: =D6+E6+F6 | H6: =G6/C6 | I6: =基础数据!H6 | J6: =I6-H6 | K6: =J6/I6
A7: P005 | B7: 定制-TP | C7: 300 | D7: 90000 | E7: 120000 | F7: 284800 | G7: =D7+E7+F7 | H7: =G7/C7 | I7: =基础数据!H7 | J7: =I7-H7 | K7: =J7/I7
A8: 合计 | C8: =SUM(C3:C7) | D8: =SUM(D3:D7) | E8: =SUM(E3:E7) | F8: =SUM(F3:F7) | G8: =SUM(G3:G7)

Sheet 成本对比
A1: 传统方法 vs ABC方法成本对比分析
A3: 单位成本对比
A4: 产品型号 | B4: 传统方法(元) | C4: ABC方法(元) | D4: 差异(元) | E4: 差异率 | F4: 分析
A5: 32315 | B5: 131.3 | C5: 120.8 | D5: =C5-B5 | E5: =D5/B5 | F5: 被高估
A6: 6320 | B6: 104.3 | C6: 95.85 | D6: =C6-B6 | E6: =D6/B6 | F6: 被高估
A7: NU2316 | B7: 158.3 | C7: 171.79 | D7: =C7-B7 | E7: =D7/B7 | F7: 被低估
A8: 定制-HD | B8: 403.3 | C8: 737.77 | D8: =C8-B8 | E8: =D8/B8 | F8: 严重低估!
A9: 定制-TP | B9: 763.17 | C9: 1649.33 | D9: =C9-B9 | E9: =D9/B9 | F9: 极度低估!
A11: 毛利率对比
A12: 产品型号 | B12: 传统方法 | C12: ABC方法 | D12: 差异 | E12: 决策影响
A13: 32315 | B13: 0.094 | C13: 0.167 | D13: =C13-B13 | E13: 比预期更好
A14: 6320 | B14: -0.134 | C14: -0.042 | D14: =C14-B14 | E14: 没那么糟
A15: NU2316 | B15: 0.435 | C15: 0.386 | D15: =C15-B15 | E15: 基本一致
A16: 定制-HD | B16: 0.776 | C16: 0.59 | D16: =C16-B16 | E16: 被高估了
A17: 定制-TP | B17: 0.861 | C17: 0.7 | D17: =C17-B17 | E17: 被显著高估!
A19: 关键发现：
A20: 1. 传统方法严重低估小批量定制品成本!
A21: 2. P005真实成本是传统方法的2.16倍!
A22: 3. 大批量标准品P001/P002成本被高估约8%
A23: 4. P001才是真正的利润贡献主力
A24: 5. P005虽高端,但成本极高,要控制规模

Sheet 可视化图表
A1: ABC成本模型可视化分析
A3: 产品单位成本对比（元）
A4: 产品型号 | B4: 传统方法 | C4: ABC方法
A5: 32315 | B5: 131.3 | C5: 120.8
A6: 6320 | B6: 104.3 | C6: 95.85
A7: NU2316 | B7: 158.3 | C7: 171.79
A8: 定制-HD | B8: 403.3 | C8: 737.77
A9: 定制-TP | B9: 763.17 | C9: 1649.33
A20: 作业成本分布
A21: 作业类别 | B21: 成本金额(元)
A22: 单位级作业 | B22: 4560000
A23: 批次级作业 | B23: 2040000
A24: 产品级作业 | B24: 620000
A25: 设施级作业 | B25: 1080000
